dinochrome_console_package/__init__.py
dinochrome_console_package/main.py
dinochrome_console_package/utils/__init__.py
dinochrome_console_package/utils/klavarog.py
dinochrome_console_package/utils/video_duration.py
dinochrome_console_package-0.0.4.dist-info/METADATA
dinochrome_console_package-0.0.4.dist-info/WHEEL
dinochrome_console_package-0.0.4.dist-info/entry_points.txt
dinochrome_console_package-0.0.4.dist-info/RECORD
